CHANGES.rst
CONTRIBUTORS.rst
DEVELOP.rst
MANIFEST.in
README.rst
TODO.rst
VERSION
setup.cfg
setup.py
docs/LICENSE.GPL
docs/LICENSE.rst
docs/index.rst
src/visaplan/__init__.py
src/visaplan.plone.animations.egg-info/PKG-INFO
src/visaplan.plone.animations.egg-info/SOURCES.txt
src/visaplan.plone.animations.egg-info/dependency_links.txt
src/visaplan.plone.animations.egg-info/entry_points.txt
src/visaplan.plone.animations.egg-info/namespace_packages.txt
src/visaplan.plone.animations.egg-info/not-zip-safe
src/visaplan.plone.animations.egg-info/requires.txt
src/visaplan.plone.animations.egg-info/top_level.txt
src/visaplan/plone/__init__.py
src/visaplan/plone/animations/__init__.py
src/visaplan/plone/animations/configure.zcml
src/visaplan/plone/animations/interfaces.py
src/visaplan/plone/animations/lapa.py
src/visaplan/plone/animations/lapainfo.py
src/visaplan/plone/animations/lapamenu.py
src/visaplan/plone/animations/metadata.py
src/visaplan/plone/animations/permissions.zcml
src/visaplan/plone/animations/profiles.zcml
src/visaplan/plone/animations/setuphandlers.py
src/visaplan/plone/animations/testing.py
src/visaplan/plone/animations/upgrades.py
src/visaplan/plone/animations/upgrades.zcml
src/visaplan/plone/animations/content/_.swp
src/visaplan/plone/animations/content/__init__.py
src/visaplan/plone/animations/content/folderish_animation.py
src/visaplan/plone/animations/content/folderish_animation.xml
src/visaplan/plone/animations/locales/visaplan.plone.animations.pot
src/visaplan/plone/animations/locales/de/LC_MESSAGES/visaplan.plone.animations.mo
src/visaplan/plone/animations/locales/de/LC_MESSAGES/visaplan.plone.animations.po
src/visaplan/plone/animations/profiles/default/browserlayer.xml
src/visaplan/plone/animations/profiles/default/catalog.xml
src/visaplan/plone/animations/profiles/default/dexterity_export-20181005164752.zip
src/visaplan/plone/animations/profiles/default/metadata.xml
src/visaplan/plone/animations/profiles/default/registry.xml
src/visaplan/plone/animations/profiles/default/rolemap.xml
src/visaplan/plone/animations/profiles/default/types.xml
src/visaplan/plone/animations/profiles/default/types/Folder.xml
src/visaplan/plone/animations/profiles/default/types/FolderishAnimation--export.xml
src/visaplan/plone/animations/profiles/default/types/FolderishAnimation.xml
src/visaplan/plone/animations/profiles/uninstall/browserlayer.xml
